setup.cfg
setup.py
gremlin/__init__.py
gremlin/cli.py
gremlin.egg-info/PKG-INFO
gremlin.egg-info/SOURCES.txt
gremlin.egg-info/dependency_links.txt
gremlin.egg-info/top_level.txt