Metadata-Version: 1.1
Name: gremlin
Version: 0.6
Summary: Curses-based command-line scripting library
Home-page: UNKNOWN
Author: Dexter Taylor (Binary Machines)
Author-email: binarymachineshop@gmail.com
License: MIT
Keywords: scripting command line curses
Platform: UNKNOWN
Classifier: License :: OSI Approved :: MIT License
Classifier: Programming Language :: Python
Classifier: Intended Audience :: Developers
Classifier: Topic :: Software Development
